[
  {
    "name": "🔎 Szél utáni szemle",
    "message": "Erős szél volt (40+ km/h). Nézz rá a támrendszerekre és a kötözésekre!",
    "type": "info",
    "conditions": { "wind_min_any": 40, "days_min": 1 }
  },
  {
    "name": "🔎 Eső utáni szemle",
    "message": "Jelentős eső esett (10mm+). Ellenőrizd a vízelvezetést és a cserepeseket!",
    "type": "info",
    "conditions": { "rain_min": 10 }
  },
  {
    "id": "extrem-hoseg",
    "name": "🌡️ Extrém Hőség",
    "type": "alert",
    "seasons": [{ "start": "06-01", "end": "08-31" }],
    "conditions": { "temp_above": 35 },
    "message": "35°C feletti hőség! Perzselő nap, védekezz mélyöntözéssel!"
  },
  {
    "id": "kanikula-tartos",
    "name": "🥵 Kánikula",
    "type": "alert",
    "seasons": [{ "start": "06-15", "end": "08-31" }],
    "conditions": { "temp_above": 30, "days_min": 2 },
    "message": "Tartós hőség. A talaj kezd kiszáradni, figyelj a vízpótlásra!"
  },
  {
    "id": "nyari-aszaly-pro",
    "name": "🔥 Aszályriadó",
    "type": "alert",
    "seasons": [{ "start": "06-01", "end": "08-31" }],
    "conditions": { "temp_above": 28, "rain_max": 2, "days_min": 5 },
    "message": "5 napja hőség van érdemi eső nélkül. Kritikus vízhiány várható!"
  },
  {
    "id": "viharos-szel-riado",
    "name": "💨 Viharos szél",
    "type": "alert",
    "conditions": { "wind_min": 39 },
    "message": "Erős széllökések várhatók. Rögzítsd a kerti eszközöket!"
  },
  {
    "id": "felhoszakadas-riado",
    "name": "🌧️ Felhőszakadás",
    "type": "alert",
    "conditions": { "rain_min": 15 },
    "message": "Intenzív esőzés (15mm+) várható. Ellenőrizd a vízelvezetőket!"
  },
  {
    "id": "mersekelt-fagy",
    "name": "❄️ Mérsékelt fagy",
    "type": "alert",
    "conditions": { "temp_below": -5 },
    "seasons": [{ "start": "11-01", "end": "03-31" }],
    "message": "Éjszaka -5°C alá hűl a levegő. Ellenőrizd a takarást!"
  },
  {
    "id": "eros-fagy-riado",
    "name": "❄️ Erős fagy",
    "type": "alert",
    "conditions": { "temp_below": -10 },
    "seasons": [{ "start": "11-01", "end": "03-15" }],
    "message": "Erős fagyok (-10°C)! Komoly fagyvédelem szükséges!"
  },
  {
    "id": "lemoso-permetezes",
    "name": "💦 Lemosó permetezés",
    "type": "window",
    "seasons": [{ "start": "02-15", "end": "03-31" }],
    "conditions": { "temp_above": 5, "wind_max": 12, "rain_max": 0 },
    "message": "Ideális idő a lemosó permetezéshez: szélcsend, fagymentesség, száraz növényzet."
  },
  {
    "id": "leveltetu-megfigyeles",
    "name": "🪲 Levéltetű figyelő",
    "type": "info",
    "seasons": [{ "start": "04-01", "end": "05-20" }],
    "conditions": { "temp_above": 12 },
    "message": "A tetvek ébredeznek. Vizsgáld a friss hajtásokat!"
  }
]
